probs_system/conversion/convert_ontology.py
probs_system/scripts/ontology-conversion/convert_rules.rdfox
probs_system/scripts/ontology-conversion/master.rdfox
probs_system/scripts/ontology-conversion/set_prefixes.rdfox
probs_system/scripts/ontology-conversion/setup-RDFox.rdfox
probs_system/tests/conftest.py
probs_system/tests/test_ontology_conversion.py
probs_module_ontology_conversion-2.0.0.dist-info/LICENSE
probs_module_ontology_conversion-2.0.0.dist-info/METADATA
probs_module_ontology_conversion-2.0.0.dist-info/WHEEL
probs_module_ontology_conversion-2.0.0.dist-info/top_level.txt
probs_module_ontology_conversion-2.0.0.dist-info/RECORD
