Metadata-Version: 2.1
Name: probs_module_ontology_conversion
Version: 2.0.0
Summary: Scripts for ontology conversion for the PRObs ontology
Author: Stefano Germano, Rick Lupton, Carla Saunders
Project-URL: Repository, https://github.com/probs-lab/probs-module-ontology-conversion
License-File: LICENSE
